LICENSE
README.md
setup.py
hgwebplus.egg-info/PKG-INFO
hgwebplus.egg-info/SOURCES.txt
hgwebplus.egg-info/dependency_links.txt
hgwebplus.egg-info/requires.txt
hgwebplus.egg-info/top_level.txt
src/hgwebplus.py
templates/static/graphv2.js
templates/static/svggraph.js