Metadata-Version: 2.1
Name: hgwebplus
Version: 0.6.4
Summary: Mercurial plugin to add additional functionality to hgweb
Home-page: https://keep.imfreedom.org/grim/hgwebplus
Author: Gary Kramlich
Author-email: grim@reaperworld.com
License: GPLv2
Platform: UNKNOWN
Classifier: Environment :: Plugins
Classifier: Intended Audience :: Developers
Classifier: Operating System :: OS Independent
Classifier: Programming Language :: Python
Classifier: License :: OSI Approved :: GNU General Public License v2 (GPLv2)
Classifier: Topic :: Software Development :: Version Control
License-File: LICENSE
